<?xml version="1.0" encoding="UTF-8"?>
<Unites>
	<CAC>
		<Caracteristiques vieMax="200" rayonUnite="15" cout="50" vitesseDeplacement="50" imageName="Vaisseau1.png" />
		<Attaque degat="100" vitesse="1000" cooldown="1000" portee="16" />
	</CAC>
	<DISTANT>
		<Caracteristiques vieMax="150" rayonUnite="11" cout="75" vitesseDeplacement="60" imageName="Vaisseau2.png" />
		<Attaque degat="80" vitesse="1000" cooldown="800" portee="50" />
	</DISTANT>
	<TANK>
		<Caracteristiques vieMax="600" rayonUnite="22" cout="150" vitesseDeplacement="35" imageName="Vaisseau3.png" />
		<Attaque degat="150" vitesse="1000" cooldown="1500" portee="23" />
	</TANK>
	
	<DEFI>
		<Caracteristiques vieMax="0" rayonUnite="15" cout="300" vitesseDeplacement="0" imageName="Defence1.png" />
		<Attaque degat="150" vitesse="2000" cooldown="1500" portee="100" />
	</DEFI>
	<DEFII>
		<Caracteristiques vieMax="0" rayonUnite="18" cout="300" vitesseDeplacement="0" imageName="Defence2.png" />
		<Attaque degat="150" vitesse="2000" cooldown="1500" portee="120" />
	</DEFII>
	<DEFIII>
		<Caracteristiques vieMax="0" rayonUnite="22" cout="300" vitesseDeplacement="0" imageName="Defence3.png" />
		<Attaque degat="150" vitesse="2000" cooldown="1500" portee="150" />
	</DEFIII>

</Unites>